Metadata-Version: 1.1
Name: dtool-tag
Version: 0.1.1
Summary: Add ability to tag datasets using the dtool CLI
Home-page: https://github.com/jic-dtool/dtool-tag
Author: Tjelvar Olsson
Author-email: tjelvar.olsson@gmail.com
License: MIT
Download-URL: https://github.com/jic-dtool/dtool-tag/tarball/0.1.1
Platform: UNKNOWN
